cvertools/__init__.py
cvertools/example.py
cvertools-1.0.3.dist-info/LICENSE
cvertools-1.0.3.dist-info/METADATA
cvertools-1.0.3.dist-info/WHEEL
cvertools-1.0.3.dist-info/top_level.txt
cvertools-1.0.3.dist-info/RECORD
