Metadata-Version: 2.1
Name: cvertools
Version: 1.0.3
Summary: A small package about small basic IO operation when coding
Home-page: https://github.com/lvzii/cvertools
Author: youshuJi
Author-email: zjs20001205@gmail.com
License: UNKNOWN
Project-URL: Bug Tracker, https://github.com/lvzii/cvertools/issues
Platform: UNKNOWN
Classifier: Programming Language :: Python :: 3
Classifier: License :: OSI Approved :: MIT License
Classifier: Operating System :: OS Independent
Requires-Python: >=3.6
License-File: LICENSE
